README.md
setup.cfg
setup.py
cambio/__init__.py
cambio.egg-info/PKG-INFO
cambio.egg-info/SOURCES.txt
cambio.egg-info/dependency_links.txt
cambio.egg-info/top_level.txt
cambio/tests/__init__.py