Metadata-Version: 2.1
Name: cambio
Version: 0.0.3
Summary: Change Python Source Code Files
Home-page: https://github.com/DanielJDufour/cambio
Author: Daniel J. Dufour
Author-email: daniel.j.dufour@gmail.com
License: UNKNOWN
Download-URL: https://github.com/DanielJDufour/cambio/tarball/download
Keywords: cli,edit,modify,python
Platform: UNKNOWN
Classifier: Development Status :: 1 - Planning
Classifier: Programming Language :: Python :: 2
Classifier: Programming Language :: Python :: 3
Classifier: License :: CC0 1.0 Universal (CC0 1.0) Public Domain Dedication
Classifier: Operating System :: OS Independent
